dkutils/__init__.py
dkutils/admin.py
dkutils/apps.py
dkutils/exceptions.py
dkutils/middleware.py
dkutils/middlewares.py
dkutils/mixins.py
dkutils/models.py
dkutils/serializers.py
dkutils/tests.py
dkutils/urls.py
dkutils/utils.py
dkutils/views.py
dkutils/migrations/__init__.py
django_dkutils-1.2.9.dist-info/LICENSE
django_dkutils-1.2.9.dist-info/METADATA
django_dkutils-1.2.9.dist-info/WHEEL
django_dkutils-1.2.9.dist-info/top_level.txt
django_dkutils-1.2.9.dist-info/RECORD
